{"cameraMode":{"drawMode":0,"name":"Shaded","section":"Shading Mode"},"sceneLighting":true,"audioPlay":false,"sceneViewState":{"m_AlwaysRefresh":false,"showFog":true,"showSkybox":true,"showFlares":true,"showImageEffects":true,"showParticleSystems":true,"showVisualEffectGraphs":true,"m_FxEnabled":true},"in2DMode":false,"pivot":{"x":15.90608024597168,"y":2.179779052734375,"z":4.6249799728393559},"rotation":{"x":0.06704682111740112,"y":0.883539617061615,"z":-0.1335626244544983,"w":0.4439830780029297},"size":0.8660253882408142,"orthographic":false}